outback/__init__.py
outback/__version__.py
outback-1.25.0.dist-info/METADATA
outback-1.25.0.dist-info/WHEEL
outback-1.25.0.dist-info/top_level.txt
outback-1.25.0.dist-info/RECORD
