Metadata-Version: 2.4
Name: outback
Version: 1.25.0
Summary: Python utilities for .NET package dependency analysis and management
Author: Outback Contributors
License-Expression: MIT
Project-URL: Homepage, https://github.com/csim/outback
Project-URL: Repository, https://github.com/csim/outback
Project-URL: Issues, https://github.com/csim/outback/issues
Keywords: dotnet,nuget,dependencies,package-management
Classifier: Development Status :: 3 - Alpha
Classifier: Intended Audience :: Developers
Classifier: Programming Language :: Python :: 3
Classifier: Programming Language :: Python :: 3.8
Classifier: Programming Language :: Python :: 3.9
Classifier: Programming Language :: Python :: 3.10
Classifier: Programming Language :: Python :: 3.11
Classifier: Programming Language :: Python :: 3.12
Classifier: Topic :: Software Development :: Libraries :: Python Modules
Requires-Python: >=3.8
Requires-Dist: rich>=10.0.0
Provides-Extra: dev
Requires-Dist: pytest>=7.0.0; extra == "dev"
Requires-Dist: black>=23.0.0; extra == "dev"
Requires-Dist: ruff>=0.1.0; extra == "dev"
Requires-Dist: mypy>=1.0.0; extra == "dev"
